{
  "version": "7",
  "dialect": "postgresql",
  "entries": [
    {
      "idx": 0,
      "version": "7",
      "when": 1768196744627,
      "tag": "0000_gorgeous_doctor_doom",
      "breakpoints": true
    },
    {
      "idx": 1,
      "version": "7",
      "when": 1768233203540,
      "tag": "0001_overconfident_galactus",
      "breakpoints": true
    },
    {
      "idx": 2,
      "version": "7",
      "when": 1768235491697,
      "tag": "0002_add_expires_at_to_transactions",
      "breakpoints": true
    }
  ]
}